{
    "author": "60 Giây Official",
    "channel_id": "UCRjzfa1E0gA50lvDQipbDMg",
    "channel_url": "https://www.youtube.com/channel/UCRjzfa1E0gA50lvDQipbDMg",
    "description": null,
    "keywords": [],
    "length": 1040,
    "publish_date": "10/07/2023",
    "thumbnail_url": "https://i.ytimg.com/vi/HuR7OyJ7MIs/hqdefault.jpg?sqp=-oaymwEXCJADEOABSFryq4qpAwkIARUAAIhCGAE=&rs=AOn4CLBus9ahRHBFqVqN0XZ8Wc-HKH45XA",
    "title": "60 Giây Chiều - Ngày 09/07/2023 - HTV Tin Tức Mới Nhất",
    "watch_url": "https://youtube.com/watch?v=HuR7OyJ7MIs"
}