{
    "author": "HTV Sports",
    "channel_id": "UC_OBG47Y3PswSHnMWSlrgZA",
    "channel_url": "https://www.youtube.com/channel/UC_OBG47Y3PswSHnMWSlrgZA",
    "description": null,
    "keywords": [],
    "length": 490,
    "publish_date": "03/04/2023",
    "thumbnail_url": "https://i.ytimg.com/vi/Jps5MfQOPTU/hq720.jpg?v=642aba65",
    "title": "Tâm tư của những tay đua “lão làng” Cúp Truyền hình TP. Hồ Chí Minh | Nhật ký đường đua 03/04/2023",
    "watch_url": "https://youtube.com/watch?v=Jps5MfQOPTU"
}