{
    "author": "Báo Tuổi Trẻ",
    "channel_id": "UC47WI-kZXFf0H_f7pvaNCEQ",
    "channel_url": "https://www.youtube.com/channel/UC47WI-kZXFf0H_f7pvaNCEQ",
    "description": null,
    "keywords": [],
    "length": 870,
    "publish_date": "14/02/2023",
    "thumbnail_url": "https://i.ytimg.com/vi/5un6NL61V_c/hq720.jpg?sqp=-oaymwEmCIAKENAF8quKqQMa8AEB-AH-CYAC0AWKAgwIABABGGUgXShPMA8=&rs=AOn4CLBkpLB50AQCQMet_mnTSngqCQqy2w",
    "title": "Góc nhìn trưa nay | Độc đáo Lễ tạ ơn rừng",
    "watch_url": "https://youtube.com/watch?v=5un6NL61V_c"
}