{
    "author": "Báo Tuổi Trẻ",
    "channel_id": "UC47WI-kZXFf0H_f7pvaNCEQ",
    "channel_url": "https://www.youtube.com/channel/UC47WI-kZXFf0H_f7pvaNCEQ",
    "description": null,
    "keywords": [],
    "length": 1095,
    "publish_date": "25/01/2023",
    "thumbnail_url": "https://i.ytimg.com/vi/g6dnGZliOXQ/hqdefault.jpg?sqp=-oaymwExCJADEOABSFryq4qpAyMIARUAAIhCGAHwAQH4Af4JgALQBYoCDAgAEAEYZSBlKGUwDw==&rs=AOn4CLAj1oUcOFdB3YBiL7paBjxx8iRpfQ",
    "title": "Góc nhìn trưa nay: Nỗi lòng bệnh nhân chạy thận ngày Tết",
    "watch_url": "https://youtube.com/watch?v=g6dnGZliOXQ"
}