{
    "author": "Báo Tuổi Trẻ",
    "channel_id": "UC47WI-kZXFf0H_f7pvaNCEQ",
    "channel_url": "https://www.youtube.com/channel/UC47WI-kZXFf0H_f7pvaNCEQ",
    "description": null,
    "keywords": [],
    "length": 799,
    "publish_date": "09/02/2023",
    "thumbnail_url": "https://i.ytimg.com/vi/P3CVRpcu6CE/hq720.jpg?sqp=-oaymwEmCIAKENAF8quKqQMa8AEB-AH-CYAC0AWKAgwIABABGFEgYihlMA8=&rs=AOn4CLCLCGAcgSasfDuPiXIx_pET93mE5g",
    "title": "Góc nhìn trưa nay | Đàn voi ở Buôn Đôn chính thức dừng cõng khách",
    "watch_url": "https://youtube.com/watch?v=P3CVRpcu6CE"
}